[
  {
    "Player":"C Rutenbar",
    "Team":"Santa Barbara Foresters",
    "G":"17",
    "AB":"65",
    "H":"22",
    "RBI":"7",
    "BB":"15",
    "2B":"6",
    "3B":"1",
    "HR":0,
    "SO":"5",
    "AVG":".338",
    "OBP":0.476,
    "SLG":0.462,
    "OPS":0.938
  },
  {
    "Player":"L Cornelison",
    "Team":"Santa Barbara Foresters",
    "G":"12",
    "AB":"30",
    "H":"7",
    "RBI":"7",
    "BB":"1",
    "2B":"1",
    "3B":"2",
    "HR":"0",
    "SO":"13",
    "AVG":".233",
    "OBP":0.258,
    "SLG":0.4,
    "OPS":0.658
  },
  {
    "Player":"C Turner",
    "Team":"Santa Barbara Foresters",
    "G":"10",
    "AB":"24",
    "H":"7",
    "RBI":"3",
    "BB":"10",
    "2B":"1",
    "3B":"1",
    "HR":"0",
    "SO":"10",
    "AVG":".292",
    "OBP":0.5,
    "SLG":0.417,
    "OPS":0.917
  }
]